microdf/__init__.py
microdf/microdataframe.py
microdf/microseries.py
microdf/tests/conftest.py
microdf/tests/test_microseries_dataframe.py
microdf/tests/test_pandas3_compatibility.py
microdf_python-1.2.1.dist-info/licenses/LICENSE
microdf_python-1.2.1.dist-info/METADATA
microdf_python-1.2.1.dist-info/WHEEL
microdf_python-1.2.1.dist-info/top_level.txt
microdf_python-1.2.1.dist-info/RECORD
