Metadata-Version: 2.4
Name: microdf-python
Version: 1.2.1
Summary: Weighted pandas DataFrames and Series for survey microdata
Author-email: Max Ghenis <max@policyengine.org>
License: MIT
Requires-Python: >=3.9
License-File: LICENSE
Requires-Dist: numpy
Requires-Dist: pandas
Provides-Extra: dev
Requires-Dist: codecov; extra == "dev"
Requires-Dist: flake8; extra == "dev"
Requires-Dist: flake8-pyproject; extra == "dev"
Requires-Dist: black; extra == "dev"
Requires-Dist: docformatter; extra == "dev"
Requires-Dist: isort; extra == "dev"
Requires-Dist: linecheck; extra == "dev"
Requires-Dist: pytest; extra == "dev"
Requires-Dist: pytest-cov; extra == "dev"
Requires-Dist: setuptools; extra == "dev"
Dynamic: license-file
